skinos/__init__.py
skinos/custom_consumer.py
celery_skinos-1.0.4.dist-info/WHEEL
celery_skinos-1.0.4.dist-info/METADATA
celery_skinos-1.0.4.dist-info/RECORD
