Metadata-Version: 2.1
Name: celery-skinos
Version: 1.0.4
Summary: Custom consumer for celery integration
Keywords: RabbitMQ,Celery
Author: DIP - Université de Strasbourg
Author-email: dnum-dip@unistra.fr
Requires-Python: >=3.8,<3.11
Classifier: Programming Language :: Python :: 3
Classifier: Programming Language :: Python :: 3.8
Classifier: Programming Language :: Python :: 3.9
Classifier: Programming Language :: Python :: 3.10
Requires-Dist: celery (>=4.2.0)
Requires-Dist: sentry-sdk (>=0.8)
